lazy_file_handler/__init__.py
lazy_file_handler/lazy_handler.py
lazy_file_handler-0.1.5.dist-info/licenses/LICENSE
lazy_file_handler-0.1.5.dist-info/METADATA
lazy_file_handler-0.1.5.dist-info/WHEEL
lazy_file_handler-0.1.5.dist-info/top_level.txt
lazy_file_handler-0.1.5.dist-info/RECORD
